examples/__init__.py
examples/qti_to_ybe.py
examples/qti_ybe_qti.py
examples/search_exams.py
examples/ybe_to_document.py
examples/ybe_to_qti.py
examples/ybe_to_ybe.py
tests/__init__.py
tests/test_ybe.py
ybe/__init__.py
ybe/__version__.py
ybe/configuration.py
ybe/cli_scripts/__init__.py
ybe/data/__init__.py
ybe/data/canvas_export.zip
ybe/data/escher.jpg
ybe/data/example_database.ybe
ybe/data/ybe.conf
ybe/data/conversion_templates/__init__.py
ybe/data/conversion_templates/html/__init__.py
ybe/data/conversion_templates/html/default/exam.html
ybe/data/conversion_templates/html/default/multiple_choice_question.html
ybe/data/conversion_templates/html/default/multiple_response_question.html
ybe/data/conversion_templates/html/default/open_question.html
ybe/data/conversion_templates/html/default/text_only_question.html
ybe/data/conversion_templates/latex/__init__.py
ybe/data/conversion_templates/latex/default/exam.tex
ybe/data/conversion_templates/latex/default/multiple_choice_question.tex
ybe/data/conversion_templates/latex/default/multiple_response_question.tex
ybe/data/conversion_templates/latex/default/open_question.tex
ybe/data/conversion_templates/latex/default/text_only_question.tex
ybe/data/conversion_templates/markdown/__init__.py
ybe/data/conversion_templates/markdown/default/exam.md
ybe/data/conversion_templates/markdown/default/multiple_choice_question.md
ybe/data/conversion_templates/markdown/default/multiple_response_question.md
ybe/data/conversion_templates/markdown/default/open_question.md
ybe/data/conversion_templates/markdown/default/text_only_question.md
ybe/data/conversion_templates/qti/__init__.py
ybe/data/conversion_templates/qti/v1p2/__init__.py
ybe/data/conversion_templates/qti/v1p2/answer_item.xml
ybe/data/conversion_templates/qti/v1p2/assessment.xml
ybe/data/conversion_templates/qti/v1p2/assessment_meta.xml
ybe/data/conversion_templates/qti/v1p2/imsmanifest.xml
ybe/data/conversion_templates/qti/v1p2/imsmanifest_resources.xml
ybe-0.3.6.dist-info/LICENSE
ybe-0.3.6.dist-info/METADATA
ybe-0.3.6.dist-info/WHEEL
ybe-0.3.6.dist-info/entry_points.txt
ybe-0.3.6.dist-info/top_level.txt
ybe-0.3.6.dist-info/RECORD
