Metadata-Version: 2.1
Name: ybe
Version: 0.3.6
Summary: Simple software package for storing exams.
Home-page: https://github.com/robbert-harms/ybe
Author: Robbert Harms
Author-email: robbert@xkls.nl
Maintainer: Robbert Harms
Maintainer-email: robbert@xkls.nl
License: GPL v3
Keywords: exams-management-system,yaml,markdown,QTI,exams,IMS Question & Test Interoperability,quiz,test,exam,assessment,LaTeX,plain-text
Platform: UNKNOWN
Classifier: Environment :: Console
Classifier: Environment :: X11 Applications :: Qt
Classifier: Intended Audience :: Developers
Classifier: Intended Audience :: Science/Research
Classifier: License :: OSI Approved :: GNU General Public License v3 or later (GPLv3+)
Classifier: Development Status :: 5 - Production/Stable
Classifier: Natural Language :: English
Classifier: Operating System :: POSIX :: Linux
Classifier: Operating System :: MacOS :: MacOS X
Classifier: Operating System :: Microsoft :: Windows
Classifier: Programming Language :: Python :: 3
Classifier: Programming Language :: Python :: 3.8
Classifier: Topic :: Scientific/Engineering
Requires-Dist: beautifulsoup4
Requires-Dist: dacite
Requires-Dist: jinja2
Requires-Dist: lxml
Requires-Dist: pypandoc
Requires-Dist: ruamel.yaml
